{"cameraMode":{"drawMode":0,"name":"Shaded","section":"Shading Mode"},"sceneLighting":false,"audioPlay":false,"sceneViewState":{"m_AlwaysRefresh":false,"showFog":true,"showSkybox":false,"showFlares":true,"showImageEffects":true,"showParticleSystems":true,"showVisualEffectGraphs":true,"m_FxEnabled":true},"in2DMode":false,"pivot":{"x":-12.471931457519532,"y":0.46733197569847109,"z":0.4798610210418701},"rotation":{"x":0.1670614629983902,"y":-0.643556535243988,"z":0.14704598486423493,"w":0.7325395941734314},"size":1.4801722764968873,"orthographic":false}